docs/hooks.py
docs/how-to/manage-multiple-datasets.py
docs/how-to/track-model-data.py
docs/how-to/version-control-pipeline.py
docs/tutorials/cloud-storage.py
docs/tutorials/commits.py
docs/tutorials/first-dataset.py
docs/tutorials/ml-workflow-script.py
docs/tutorials/ml-workflow.py
kirin/__init__.py
kirin/auth_helpers.py
kirin/catalog.py
kirin/cli.py
kirin/cloud_auth.py
kirin/commit.py
kirin/commit_store.py
kirin/dataset.py
kirin/file.py
kirin/html_repr.py
kirin/keyring_store.py
kirin/ml_artifacts.py
kirin/plots.py
kirin/preprocessing.py
kirin/schemas.py
kirin/setup_ssl.py
kirin/storage.py
kirin/testing_utils.py
kirin/utils.py
kirin/web/__init__.py
kirin/web/app.py
kirin/web/config.py
kirin/web/models.py
kirin/web/static/styles.css
kirin/web/templates/base.html
kirin/web/templates/catalog_form.html
kirin/web/templates/catalogs.html
kirin/web/templates/commit_form.html
kirin/web/templates/dataset_view.html
kirin/web/templates/datasets.html
kirin/web/templates/delete_catalog.html
kirin/web/templates/file_preview.html
kirin/web/templates/files_tab.html
kirin/web/templates/history_tab.html
kirin/widgets/__init__.py
kirin/widgets/base.py
kirin/widgets/catalog.py
kirin/widgets/commit.py
kirin/widgets/dataset.py
kirin/widgets/file_list.py
kirin/widgets/utils.py
kirin/widgets/assets/catalog.js
kirin/widgets/assets/commit.js
kirin/widgets/assets/dataset.js
kirin/widgets/assets/file_interactions.js
kirin/widgets/assets/file_list.js
kirin/widgets/assets/panel_utils.js
kirin/widgets/assets/shared.css
kirin/widgets/assets/ui_utils.js
kirin/widgets/templates/catalog.html
kirin/widgets/templates/commit.html
kirin/widgets/templates/dataset.html
kirin/widgets/templates/macros.html
notebooks/catalog_demo.py
notebooks/gcp_storage_demo.py
notebooks/gitdata_linear_workflow_demo.py
notebooks/kirin_version_plots.py
notebooks/local_demo.py
notebooks/model_versioning_demo.py
notebooks/scratch.py
notebooks/test_plot_source_linking.py
notebooks/test_source_detection_minimal.py
kirin-0.0.11.dist-info/METADATA
kirin-0.0.11.dist-info/WHEEL
kirin-0.0.11.dist-info/entry_points.txt
kirin-0.0.11.dist-info/top_level.txt
kirin-0.0.11.dist-info/RECORD
