Metadata-Version: 2.4
Name: kirin
Version: 0.0.11
Requires-Dist: pyprojroot
Requires-Dist: python-dotenv
Requires-Dist: typer
Requires-Dist: json5
Requires-Dist: fsspec
Requires-Dist: s3fs
Requires-Dist: gcsfs
Requires-Dist: fastapi
Requires-Dist: jinja2
Requires-Dist: python-multipart
Requires-Dist: python-slugify
Requires-Dist: keyring
Requires-Dist: boto3
Requires-Dist: loguru
Requires-Dist: uvicorn
Requires-Dist: ipynbname
Requires-Dist: pillow
Requires-Dist: anywidget
